README.rst
setup.py
httxlib/__init__.py
httxlib/httxauth.py
httxlib/httxauthcache.py
httxlib/httxbase.py
httxlib/httxcertificates.py
httxlib/httxcompression.py
httxlib/httxcompressionset.py
httxlib/httxconnection.py
httxlib/httxcookiejar.py
httxlib/httxerror.py
httxlib/httxmanager.py
httxlib/httxnetlocation.py
httxlib/httxobject.py
httxlib/httxoptions.py
httxlib/httxpassmanager.py
httxlib/httxrequest.py
httxlib/httxresponse.py
httxlib/httxs.py
httxlib/httxutil.py
httxlib/version.py
httxlib.egg-info/PKG-INFO
httxlib.egg-info/SOURCES.txt
httxlib.egg-info/dependency_links.txt
httxlib.egg-info/top_level.txt