Metadata-Version: 1.1
Name: httxlib
Version: 1.0.4
Summary: HTTP(s) Library
Home-page: https://github.com/mementum/httxlib
Author: Daniel Rodriguez
Author-email: danjrod@gmail.com
License: GPLv2+
Download-URL: https://github.com/mementum/httxlib/tarball/1.0.4
Keywords: networking,http,https,development
Platform: UNKNOWN
Classifier: Development Status :: 5 - Production/Stable
Classifier: Intended Audience :: Developers
Classifier: Intended Audience :: Telecommunications Industry
Classifier: Intended Audience :: Information Technology
Classifier: Topic :: Software Development
Classifier: Topic :: Office/Business :: Financial
Classifier: License :: OSI Approved :: GNU General Public License v2 or later (GPLv2+)
Classifier: Programming Language :: Python :: 2
Classifier: Programming Language :: Python :: 2.7
Classifier: Operating System :: OS Independent
